basketcase/__init__.py
basketcase/__main__.py
basketcase/basketcase.py
basketcase/extractor.py
basketcase/models.py
basketcase/storage.py
basketcase/migrations/__init__.py
basketcase/migrations/v1/__init__.py
basketcase/migrations/v2/__init__.py
basketcase/migrations/v3/__init__.py
basketcase-8.0.0.dist-info/licenses/LICENSE
basketcase-8.0.0.dist-info/METADATA
basketcase-8.0.0.dist-info/WHEEL
basketcase-8.0.0.dist-info/entry_points.txt
basketcase-8.0.0.dist-info/top_level.txt
basketcase-8.0.0.dist-info/RECORD
