Metadata-Version: 2.4
Name: basketcase
Version: 8.0.0
Summary: Download media from Instagram
Author-email: Douglas Silva <doug.hs@proton.me>
License-Expression: GPL-3.0-or-later
Project-URL: Homepage, https://gitlab.com/crimson.king/basketcase
Project-URL: Bug Tracker, https://gitlab.com/crimson.king/basketcase/-/issues
Keywords: instagram,story,stories
Classifier: Programming Language :: Python :: 3
Classifier: Operating System :: OS Independent
Requires-Python: >=3.10
License-File: LICENSE
Requires-Dist: httpx[brotli,zstd]~=0.28
Requires-Dist: beautifulsoup4~=4.13
Requires-Dist: lxml~=6.0
Requires-Dist: pillow~=12.0
Dynamic: license-file
